gero/nlp_workbench/Corpus.py
gero/nlp_workbench/Document.py
gero/nlp_workbench/__init__.py
gero_nlp_workbench-0.0.5.dist-info/METADATA
gero_nlp_workbench-0.0.5.dist-info/WHEEL
gero_nlp_workbench-0.0.5.dist-info/top_level.txt
gero_nlp_workbench-0.0.5.dist-info/RECORD
