Metadata-Version: 2.1
Name: gero-nlp-workbench
Version: 0.0.5
Summary: A simple NLP workbench.
Author-email: Gerome Meyer <meyerger@students.zhaw.ch>
Project-URL: Homepage, https://github.com/GeroVanMi/NLP_Project_Workbench
Keywords: nlp,natural language processing,example,workbench,toolkit
Classifier: License :: OSI Approved :: MIT License
Classifier: Programming Language :: Python
Classifier: Programming Language :: Python :: 3
Requires-Python: >=3.10
Requires-Dist: nltk (>=3.8.0)
Requires-Dist: wordcloud (~=1.8.2.2)
Requires-Dist: matplotlib (~=3.6.2)
